sin/__init__.py
sin-0.0.1.dist-info/METADATA
sin-0.0.1.dist-info/WHEEL
sin-0.0.1.dist-info/top_level.txt
sin-0.0.1.dist-info/RECORD
